robotime/__init__.py
robotime/clocks.py
robotime/test.py
robotime/time.py
robo_time-0.1.9.dist-info/LICENSE
robo_time-0.1.9.dist-info/METADATA
robo_time-0.1.9.dist-info/WHEEL
robo_time-0.1.9.dist-info/top_level.txt
robo_time-0.1.9.dist-info/RECORD
