Metadata-Version: 2.1
Name: robo-time
Version: 0.1.9
Summary: Clocks, timing, timestamps for mobile robotics
Home-page: https://github.com/mkner/robo-time
Author: Mike Knerr
License: BSD
Keywords: mobile robotics, time, timing, time sync, timestamps,,clocks, system clock, uptime clock, sync clock,,RFC-3339, ISO-8601, UTC time, NTP time
Platform: UNKNOWN
Classifier: Programming Language :: Python :: 3
Classifier: License :: OSI Approved :: BSD License
Classifier: Operating System :: OS Independent
License-File: LICENSE
Requires-Dist: robo-base (>=0.1.3)
